eboekhouden_python/__init__.py
eboekhouden_python/eboekhouden_client.py
eboekhouden_python/constants/__init__.py
eboekhouden_python/constants/bedrijf_particulier.py
eboekhouden_python/constants/btw_code.py
eboekhouden_python/constants/in_ex_btw.py
eboekhouden_python/constants/mutatie_soort.py
eboekhouden_python/constants/open_post_soort.py
eboekhouden_python/constants/string_enum.py
eboekhouden_python/models/__init__.py
eboekhouden_python/models/mutatie.py
eboekhouden_python/models/mutatie_filter.py
eboekhouden_python/models/mutatie_regel.py
eboekhouden_python/models/open_post.py
eboekhouden_python/models/relatie.py
eboekhouden_python/models/relatie_filter.py
eboekhouden_python-0.4.2.dist-info/METADATA
eboekhouden_python-0.4.2.dist-info/WHEEL
eboekhouden_python-0.4.2.dist-info/licenses/LICENSE
eboekhouden_python-0.4.2.dist-info/RECORD
