Metadata-Version: 2.4
Name: eboekhouden-python
Version: 0.4.2
Summary: This is a simple API client for the E-boekhouden.nl API. It is written in Python and uses the ZEEP library.
Project-URL: Homepage, https://github.com/dennisbakhuis/eboekhouden-python
Project-URL: Repository, https://github.com/dennisbakhuis/eboekhouden-python
Author-email: Dennis Bakhuis <pypi@bakhuis.nu>
License: MIT
License-File: LICENSE
Keywords: api,client,e-boekhouden,eboekhouden,python,soap,zeep
Classifier: Development Status :: 4 - Beta
Classifier: Intended Audience :: Developers
Classifier: License :: OSI Approved :: MIT License
Classifier: Programming Language :: Python :: 3
Classifier: Programming Language :: Python :: 3.10
Classifier: Programming Language :: Python :: 3.11
Classifier: Programming Language :: Python :: 3.12
Classifier: Programming Language :: Python :: 3.13
Requires-Python: >=3.10
Requires-Dist: zeep>=4.3.1
Provides-Extra: dev
Requires-Dist: coverage>=7.6.10; extra == 'dev'
Requires-Dist: jupyter>=1.1.1; extra == 'dev'
Requires-Dist: jupyterlab>=4.3.4; extra == 'dev'
Requires-Dist: packaging>=23.0; extra == 'dev'
Requires-Dist: pre-commit>=4.0.1; extra == 'dev'
Requires-Dist: pytest-cov>=6.0.0; extra == 'dev'
Requires-Dist: pytest>=8.3.4; extra == 'dev'
Requires-Dist: tomli>=2.2.1; extra == 'dev'
